domovyk/.DS_Store
domovyk/__init__.py
domovyk/bel.py
domovyk/bulg.py
domovyk/carp.py
domovyk/church.py
domovyk/mac.py
domovyk/rus.py
domovyk/serb.py
domovyk/translit.py
domovyk/ukr.py
domovyk-1.0.1.dist-info/METADATA
domovyk-1.0.1.dist-info/WHEEL
domovyk-1.0.1.dist-info/licenses/LICENSE
domovyk-1.0.1.dist-info/RECORD
