Metadata-Version: 2.1
Name: domovyk
Version: 1.0.1
Summary: A tool to easily transliterate text to and from various Cyrillic alphabets.
Project-URL: Homepage, https://github.com/ian-nai/domovyk
Project-URL: Bug Tracker, https://github.com/ian-nai/domovyk/issues
Author-email: Ian Goodale <ian.goodale@austin.utexas.edu>
License: GNU GENERAL PUBLIC LICENSE
License-File: LICENSE
Classifier: License :: OSI Approved :: GNU General Public License v3 (GPLv3)
Classifier: Operating System :: OS Independent
Classifier: Programming Language :: Python :: 3
Requires-Python: >=3.7
Requires-Dist: nltk==3.6.5
